microblocks_wifi_radio/__init__.py
microblocks_wifi_radio-0.6.0.dist-info/METADATA
microblocks_wifi_radio-0.6.0.dist-info/WHEEL
microblocks_wifi_radio-0.6.0.dist-info/RECORD
