Metadata-Version: 2.1
Name: microblocks-wifi-radio
Version: 0.6.0
Summary: 
Author: wwj718
Author-email: wuwenjie718@gmail.com
Requires-Python: >=3.7,<4.0
Classifier: Programming Language :: Python :: 3
Classifier: Programming Language :: Python :: 3.7
Classifier: Programming Language :: Python :: 3.8
Classifier: Programming Language :: Python :: 3.9
Classifier: Programming Language :: Python :: 3.10
Classifier: Programming Language :: Python :: 3.11
